utils/__init__.py
utils/arguments_util.py
utils/config_util.py
utils/html_generator_util.py
cool_ssg_lmpham1-1.0.0.dist-info/LICENSE
cool_ssg_lmpham1-1.0.0.dist-info/METADATA
cool_ssg_lmpham1-1.0.0.dist-info/WHEEL
cool_ssg_lmpham1-1.0.0.dist-info/top_level.txt
cool_ssg_lmpham1-1.0.0.dist-info/RECORD
