Metadata-Version: 2.1
Name: cool-ssg-lmpham1
Version: 1.0.0
Summary: A CLI static site generator written in Python
Home-page: https://github.com/lmpham1/cool_ssg_generator
Author: Le Minh Pham
Author-email: lmpham1@myseneca.ca
License: UNKNOWN
Project-URL: Bug Tracker, https://github.com/lmpham1/cool_ssg_generator/issues
Platform: UNKNOWN
Classifier: Programming Language :: Python :: 3
Classifier: License :: OSI Approved :: MIT License
Classifier: Operating System :: OS Independent
Requires-Python: >=3.6
License-File: LICENSE
